{
  "FR;RB;FL;F2, R S' R'": {
    "buffer": "FR",
    "first_target": "RB",
    "second_target": "FL",
    "results": [],
    "latest": true,
    "alg": "F2, R S' R'",
    "lp": "WI"
  },
  "FR;RD;FL;u: L/S": {
    "buffer": "FR",
    "first_target": "RD",
    "second_target": "FL",
    "results": [],
    "latest": true,
    "alg": "u: L/S",
    "lp": "ZI"
  },
  "FR;BL;FL;E', L2": {
    "buffer": "FR",
    "first_target": "BL",
    "second_target": "FL",
    "results": [],
    "latest": true,
    "alg": "E', L2",
    "lp": "MI"
  },
  "FR;BR;FL;R2, E": {
    "buffer": "FR",
    "first_target": "BR",
    "second_target": "FL",
    "results": [],
    "latest": true,
    "alg": "R2, E",
    "lp": "NI"
  },
  "FR;LD;FL;u': R/S'": {
    "buffer": "FR",
    "first_target": "LD",
    "second_target": "FL",
    "results": [],
    "latest": true,
    "alg": "u': R/S'",
    "lp": "TI"
  },
  "FR;LB;FL;L' S L, F2": {
    "buffer": "FR",
    "first_target": "LB",
    "second_target": "FL",
    "results": [],
    "latest": true,
    "alg": "L' S L, F2",
    "lp": "RI"
  },
  "FR;DR;FL;R U R' U': R/E": {
    "buffer": "FR",
    "first_target": "DR",
    "second_target": "FL",
    "results": [],
    "latest": true,
    "alg": "R U R' U': R/E",
    "lp": "FI"
  },
  "FR;DL;FL;L' U' L U: L/E'": {
    "buffer": "FR",
    "first_target": "DL",
    "second_target": "FL",
    "results": [],
    "latest": true,
    "alg": "L' U' L U: L/E'",
    "lp": "EI"
  },
  "FR;FL;RB;R S' R', F2": {
    "buffer": "FR",
    "first_target": "FL",
    "second_target": "RB",
    "results": [],
    "latest": true,
    "alg": "R S' R', F2",
    "lp": "IW"
  },
  "FR;RD;RB;R: U R' U', S": {
    "buffer": "FR",
    "first_target": "RD",
    "second_target": "RB",
    "results": [],
    "latest": true,
    "alg": "R: U R' U', S",
    "lp": "ZW"
  },
  "FR;BL;RB;R': S, R' B2 R": {
    "buffer": "FR",
    "first_target": "BL",
    "second_target": "RB",
    "results": [],
    "latest": true,
    "alg": "R': S, R' B2 R",
    "lp": "MW"
  },
  "FR;LF;RB;R': R' F2 R, S'": {
    "buffer": "FR",
    "first_target": "LF",
    "second_target": "RB",
    "results": [],
    "latest": true,
    "alg": "R': R' F2 R, S'",
    "lp": "SW"
  },
  "FR;LD;RB;L F' L' U: L/E": {
    "buffer": "FR",
    "first_target": "LD",
    "second_target": "RB",
    "results": [],
    "latest": true,
    "alg": "L F' L' U: L/E",
    "lp": "TW"
  },
  "FR;LB;RB;B2, R' S' R": {
    "buffer": "FR",
    "first_target": "LB",
    "second_target": "RB",
    "results": [],
    "latest": true,
    "alg": "B2, R' S' R",
    "lp": "RW"
  },
  "FR;DR;RB;R2 u': R' U R, E'": {
    "buffer": "FR",
    "first_target": "DR",
    "second_target": "RB",
    "results": [],
    "latest": true,
    "alg": "R2 u': R' U R, E'",
    "lp": "FW"
  },
  "FR;DL;RB;L' B L U': L/E'": {
    "buffer": "FR",
    "first_target": "DL",
    "second_target": "RB",
    "results": [],
    "latest": true,
    "alg": "L' B L U': L/E'",
    "lp": "EW"
  },
  "FR;FL;RD;u: L'/S": {
    "buffer": "FR",
    "first_target": "FL",
    "second_target": "RD",
    "results": [],
    "latest": true,
    "alg": "u: L'/S",
    "lp": "IZ"
  },
  "FR;RB;RD;R: S, U R' U'": {
    "buffer": "FR",
    "first_target": "RB",
    "second_target": "RD",
    "results": [],
    "latest": true,
    "alg": "R: S, U R' U'",
    "lp": "WZ"
  },
  "FR;BL;RD;R u' R': R' E R, U": {
    "buffer": "FR",
    "first_target": "BL",
    "second_target": "RD",
    "results": [],
    "latest": true,
    "alg": "R u' R': R' E R, U",
    "lp": "MZ"
  },
  "FR;BR;RD;S: R/S'": {
    "buffer": "FR",
    "first_target": "BR",
    "second_target": "RD",
    "results": [],
    "latest": true,
    "alg": "S: R/S'",
    "lp": "NZ"
  },
  "FR;LF;RD;r E': L'/S'": {
    "buffer": "FR",
    "first_target": "LF",
    "second_target": "RD",
    "results": [],
    "latest": true,
    "alg": "r E': L'/S'",
    "lp": "SZ"
  },
  "FR;LD;RD;S: L'/E'": {
    "buffer": "FR",
    "first_target": "LD",
    "second_target": "RD",
    "results": [],
    "latest": true,
    "alg": "S: L'/E'",
    "lp": "TZ"
  },
  "FR;LB;RD;L' S: L'/E'": {
    "buffer": "FR",
    "first_target": "LB",
    "second_target": "RD",
    "results": [],
    "latest": true,
    "alg": "L' S: L'/E'",
    "lp": "RZ"
  },
  "FR;DL;RD;L' F2 L, S": {
    "buffer": "FR",
    "first_target": "DL",
    "second_target": "RD",
    "results": [],
    "latest": true,
    "alg": "L' F2 L, S",
    "lp": "EZ"
  },
  "FR;FL;BL;L2, E'": {
    "buffer": "FR",
    "first_target": "FL",
    "second_target": "BL",
    "results": [],
    "latest": true,
    "alg": "L2, E'",
    "lp": "IM"
  },
  "FR;RB;BL;R': R' B2 R, S": {
    "buffer": "FR",
    "first_target": "RB",
    "second_target": "BL",
    "results": [],
    "latest": true,
    "alg": "R': R' B2 R, S",
    "lp": "WM"
  },
  "FR;RD;BL;R u' R': U, R' E R": {
    "buffer": "FR",
    "first_target": "RD",
    "second_target": "BL",
    "results": [],
    "latest": true,
    "alg": "R u' R': U, R' E R",
    "lp": "ZM"
  },
  "FR;BR;BL;E', R2": {
    "buffer": "FR",
    "first_target": "BR",
    "second_target": "BL",
    "results": [],
    "latest": true,
    "alg": "E', R2",
    "lp": "NM"
  },
  "FR;LF;BL;L: S, L F2 L'": {
    "buffer": "FR",
    "first_target": "LF",
    "second_target": "BL",
    "results": [],
    "latest": true,
    "alg": "L: S, L F2 L'",
    "lp": "SM"
  },
  "FR;LD;BL;L u' L': L' E L, U": {
    "buffer": "FR",
    "first_target": "LD",
    "second_target": "BL",
    "results": [],
    "latest": true,
    "alg": "L u' L': L' E L, U",
    "lp": "TM"
  },
  "FR;DR;BL;R U R' U': R'/E'": {
    "buffer": "FR",
    "first_target": "DR",
    "second_target": "BL",
    "results": [],
    "latest": true,
    "alg": "R U R' U': R'/E'",
    "lp": "FM"
  },
  "FR;DL;BL;L U' L' U: L/E'": {
    "buffer": "FR",
    "first_target": "DL",
    "second_target": "BL",
    "results": [],
    "latest": true,
    "alg": "L U' L' U: L/E'",
    "lp": "EM"
  },
  "FR;FL;BR;E, R2": {
    "buffer": "FR",
    "first_target": "FL",
    "second_target": "BR",
    "results": [],
    "latest": true,
    "alg": "E, R2",
    "lp": "IN"
  },
  "FR;RD;BR;S: R'/S'": {
    "buffer": "FR",
    "first_target": "RD",
    "second_target": "BR",
    "results": [],
    "latest": true,
    "alg": "S: R'/S'",
    "lp": "ZN"
  },
  "FR;BL;BR;R2, E'": {
    "buffer": "FR",
    "first_target": "BL",
    "second_target": "BR",
    "results": [],
    "latest": true,
    "alg": "R2, E'",
    "lp": "MN"
  },
  "FR;LF;BR;R E': R/E'": {
    "buffer": "FR",
    "first_target": "LF",
    "second_target": "BR",
    "results": [],
    "latest": true,
    "alg": "R E': R/E'",
    "lp": "SN"
  },
  "FR;LD;BR;S: R/S": {
    "buffer": "FR",
    "first_target": "LD",
    "second_target": "BR",
    "results": [],
    "latest": true,
    "alg": "S: R/S",
    "lp": "TN"
  },
  "FR;LB;BR;R E: R'/E": {
    "buffer": "FR",
    "first_target": "LB",
    "second_target": "BR",
    "results": [],
    "latest": true,
    "alg": "R E: R'/E",
    "lp": "RN"
  },
  "FR;DR;BR;u2: L'/S": {
    "buffer": "FR",
    "first_target": "DR",
    "second_target": "BR",
    "results": [],
    "latest": true,
    "alg": "u2: L'/S",
    "lp": "FN"
  },
  "FR;DL;BR;R'/S'": {
    "buffer": "FR",
    "first_target": "DL",
    "second_target": "BR",
    "results": [],
    "latest": true,
    "alg": "R'/S'",
    "lp": "EN"
  },
  "FR;RB;LF;R': S', R' F2 R": {
    "buffer": "FR",
    "first_target": "RB",
    "second_target": "LF",
    "results": [],
    "latest": true,
    "alg": "R': S', R' F2 R",
    "lp": "WS"
  },
  "FR;RD;LF;r E': L/S'": {
    "buffer": "FR",
    "first_target": "RD",
    "second_target": "LF",
    "results": [],
    "latest": true,
    "alg": "r E': L/S'",
    "lp": "ZS"
  },
  "FR;BL;LF;L: L F2 L', S": {
    "buffer": "FR",
    "first_target": "BL",
    "second_target": "LF",
    "results": [],
    "latest": true,
    "alg": "L: L F2 L', S",
    "lp": "MS"
  },
  "FR;BR;LF;R E': R'/E'": {
    "buffer": "FR",
    "first_target": "BR",
    "second_target": "LF",
    "results": [],
    "latest": true,
    "alg": "R E': R'/E'",
    "lp": "NS"
  },
  "FR;LD;LF;S' R' S, l": {
    "buffer": "FR",
    "first_target": "LD",
    "second_target": "LF",
    "results": [],
    "latest": true,
    "alg": "S' R' S, l",
    "lp": "TS"
  },
  "FR;LB;LF;E: F2, R S' R'": {
    "buffer": "FR",
    "first_target": "LB",
    "second_target": "LF",
    "results": [],
    "latest": true,
    "alg": "E: F2, R S' R'",
    "lp": "RS"
  },
  "FR;DR;LF;R2 U R': R' E R, U'": {
    "buffer": "FR",
    "first_target": "DR",
    "second_target": "LF",
    "results": [],
    "latest": true,
    "alg": "R2 U R': R' E R, U'",
    "lp": "FS"
  },
  "FR;DL;LF;R' S': R/E": {
    "buffer": "FR",
    "first_target": "DL",
    "second_target": "LF",
    "results": [],
    "latest": true,
    "alg": "R' S': R/E",
    "lp": "ES"
  },
  "FR;FL;LD;u': R'/S'": {
    "buffer": "FR",
    "first_target": "FL",
    "second_target": "LD",
    "results": [],
    "latest": true,
    "alg": "u': R'/S'",
    "lp": "IT"
  },
  "FR;RB;LD;L F' L' U: L'/E": {
    "buffer": "FR",
    "first_target": "RB",
    "second_target": "LD",
    "results": [],
    "latest": true,
    "alg": "L F' L' U: L'/E",
    "lp": "WT"
  },
  "FR;RD;LD;S: L/E'": {
    "buffer": "FR",
    "first_target": "RD",
    "second_target": "LD",
    "results": [],
    "latest": true,
    "alg": "S: L/E'",
    "lp": "ZT"
  },
  "FR;BL;LD;L u' L': U, L' E L": {
    "buffer": "FR",
    "first_target": "BL",
    "second_target": "LD",
    "results": [],
    "latest": true,
    "alg": "L u' L': U, L' E L",
    "lp": "MT"
  },
  "FR;BR;LD;S: R'/S": {
    "buffer": "FR",
    "first_target": "BR",
    "second_target": "LD",
    "results": [],
    "latest": true,
    "alg": "S: R'/S",
    "lp": "NT"
  },
  "FR;LF;LD;l, S' R' S": {
    "buffer": "FR",
    "first_target": "LF",
    "second_target": "LD",
    "results": [],
    "latest": true,
    "alg": "l, S' R' S",
    "lp": "ST"
  },
  "FR;LB;LD;L2 u: L' U' L, E": {
    "buffer": "FR",
    "first_target": "LB",
    "second_target": "LD",
    "results": [],
    "latest": true,
    "alg": "L2 u: L' U' L, E",
    "lp": "RT"
  },
  "FR;DR;LD;U R' U', S'": {
    "buffer": "FR",
    "first_target": "DR",
    "second_target": "LD",
    "results": [],
    "latest": true,
    "alg": "U R' U', S'",
    "lp": "FT"
  },
  "FR;FL;LB;F2, L' S L": {
    "buffer": "FR",
    "first_target": "FL",
    "second_target": "LB",
    "results": [],
    "latest": true,
    "alg": "F2, L' S L",
    "lp": "IR"
  },
  "FR;RB;LB;R' S' R, B2": {
    "buffer": "FR",
    "first_target": "RB",
    "second_target": "LB",
    "results": [],
    "latest": true,
    "alg": "R' S' R, B2",
    "lp": "WR"
  },
  "FR;RD;LB;L' S: L/E'": {
    "buffer": "FR",
    "first_target": "RD",
    "second_target": "LB",
    "results": [],
    "latest": true,
    "alg": "L' S: L/E'",
    "lp": "ZR"
  },
  "FR;BR;LB;R E: R/E": {
    "buffer": "FR",
    "first_target": "BR",
    "second_target": "LB",
    "results": [],
    "latest": true,
    "alg": "R E: R/E",
    "lp": "NR"
  },
  "FR;LF;LB;E: R S' R', F2": {
    "buffer": "FR",
    "first_target": "LF",
    "second_target": "LB",
    "results": [],
    "latest": true,
    "alg": "E: R S' R', F2",
    "lp": "SR"
  },
  "FR;LD;LB;L2 U: L' U' L, E'": {
    "buffer": "FR",
    "first_target": "LD",
    "second_target": "LB",
    "results": [],
    "latest": true,
    "alg": "L2 U: L' U' L, E'",
    "lp": "TR"
  },
  "FR;DR;LB;R u R': R' E R, U'": {
    "buffer": "FR",
    "first_target": "DR",
    "second_target": "LB",
    "results": [],
    "latest": true,
    "alg": "R u R': R' E R, U'",
    "lp": "FR"
  },
  "FR;DL;LB;R' S': R'/E'": {
    "buffer": "FR",
    "first_target": "DL",
    "second_target": "LB",
    "results": [],
    "latest": true,
    "alg": "R' S': R'/E'",
    "lp": "ER"
  },
  "FR;FL;DR;R U R' U': R'/E": {
    "buffer": "FR",
    "first_target": "FL",
    "second_target": "DR",
    "results": [],
    "latest": true,
    "alg": "R U R' U': R'/E",
    "lp": "IF"
  },
  "FR;RB;DR;R2 U': R' U R, E": {
    "buffer": "FR",
    "first_target": "RB",
    "second_target": "DR",
    "results": [],
    "latest": true,
    "alg": "R2 U': R' U R, E",
    "lp": "WF"
  },
  "FR;BL;DR;R U R' U': R/E'": {
    "buffer": "FR",
    "first_target": "BL",
    "second_target": "DR",
    "results": [],
    "latest": true,
    "alg": "R U R' U': R/E'",
    "lp": "MF"
  },
  "FR;BR;DR;u2: L/S": {
    "buffer": "FR",
    "first_target": "BR",
    "second_target": "DR",
    "results": [],
    "latest": true,
    "alg": "u2: L/S",
    "lp": "NF"
  },
  "FR;LF;DR;R2 U R': U', R' E R": {
    "buffer": "FR",
    "first_target": "LF",
    "second_target": "DR",
    "results": [],
    "latest": true,
    "alg": "R2 U R': U', R' E R",
    "lp": "SF"
  },
  "FR;LD;DR;S', U R' U'": {
    "buffer": "FR",
    "first_target": "LD",
    "second_target": "DR",
    "results": [],
    "latest": true,
    "alg": "S', U R' U'",
    "lp": "TF"
  },
  "FR;LB;DR;R u R': U', R' E R": {
    "buffer": "FR",
    "first_target": "LB",
    "second_target": "DR",
    "results": [],
    "latest": true,
    "alg": "R u R': U', R' E R",
    "lp": "RF"
  },
  "FR;DL;DR;L F2: L'/S": {
    "buffer": "FR",
    "first_target": "DL",
    "second_target": "DR",
    "results": [],
    "latest": true,
    "alg": "L F2: L'/S",
    "lp": "EF"
  },
  "FR;FL;DL;L' U' L U: L'/E'": {
    "buffer": "FR",
    "first_target": "FL",
    "second_target": "DL",
    "results": [],
    "latest": true,
    "alg": "L' U' L U: L'/E'",
    "lp": "IE"
  },
  "FR;RB;DL;L' B L U': L'/E'": {
    "buffer": "FR",
    "first_target": "RB",
    "second_target": "DL",
    "results": [],
    "latest": true,
    "alg": "L' B L U': L'/E'",
    "lp": "WE"
  },
  "FR;RD;DL;S, L' F2 L": {
    "buffer": "FR",
    "first_target": "RD",
    "second_target": "DL",
    "results": [],
    "latest": true,
    "alg": "S, L' F2 L",
    "lp": "ZE"
  },
  "FR;BL;DL;L U' L' U: L'/E'": {
    "buffer": "FR",
    "first_target": "BL",
    "second_target": "DL",
    "results": [],
    "latest": true,
    "alg": "L U' L' U: L'/E'",
    "lp": "ME"
  },
  "FR;BR;DL;R/S'": {
    "buffer": "FR",
    "first_target": "BR",
    "second_target": "DL",
    "results": [],
    "latest": true,
    "alg": "R/S'",
    "lp": "NE"
  },
  "FR;LF;DL;R' S': R'/E": {
    "buffer": "FR",
    "first_target": "LF",
    "second_target": "DL",
    "results": [],
    "latest": true,
    "alg": "R' S': R'/E",
    "lp": "SE"
  },
  "FR;LB;DL;R' S': R/E'": {
    "buffer": "FR",
    "first_target": "LB",
    "second_target": "DL",
    "results": [],
    "latest": true,
    "alg": "R' S': R/E'",
    "lp": "RE"
  },
  "FR;DR;DL;L F2: L/S": {
    "buffer": "FR",
    "first_target": "DR",
    "second_target": "DL",
    "results": [],
    "latest": true,
    "alg": "L F2: L/S",
    "lp": "FE"
  }
}